getnative/__init__.py
getnative/__main__.py
getnative/app.py
getnative/utils.py
getnative-3.3.0.dist-info/licenses/LICENSE
getnative-3.3.0.dist-info/METADATA
getnative-3.3.0.dist-info/WHEEL
getnative-3.3.0.dist-info/entry_points.txt
getnative-3.3.0.dist-info/top_level.txt
getnative-3.3.0.dist-info/RECORD
