Metadata-Version: 2.4
Name: getnative
Version: 3.3.0
Summary: Find the native resolution(s) of upscaled material (mostly anime)
Home-page: https://github.com/Infiziert90/getnative
Author: Infi, Kageru
Author-email: infiziert@protonmail.ch, kageru@encode.moe
Classifier: Programming Language :: Python :: 3
Classifier: License :: OSI Approved :: MIT License
Classifier: Operating System :: OS Independent
Requires-Python: >=3.6
License-File: LICENSE
Requires-Dist: matplotlib>=2.0.0
Requires-Dist: VapourSynth>=71
Dynamic: author
Dynamic: author-email
Dynamic: classifier
Dynamic: description
Dynamic: description-content-type
Dynamic: home-page
Dynamic: license-file
Dynamic: requires-dist
Dynamic: requires-python
Dynamic: summary
